secbench/api/__init__.py
secbench/api/_utils.py
secbench/api/bench.py
secbench/api/discovery.py
secbench/api/enums.py
secbench/api/exceptions.py
secbench/api/helpers.py
secbench/api/hooks.py
secbench/api/types.py
secbench/api/backend/__init__.py
secbench/api/backend/pyvisa.py
secbench/api/backend/serial.py
secbench/api/backend/types.py
secbench/api/backend/usbtmc.py
secbench/api/backend/vxi11.py
secbench/api/instrument/__init__.py
secbench/api/instrument/afg.py
secbench/api/instrument/features.py
secbench/api/instrument/psu.py
secbench/api/instrument/pulser.py
secbench/api/instrument/scope.py
secbench/api/instrument/table.py
secbench/api/instrument/types.py
secbench/api/simulation/__init__.py
secbench/api/simulation/pulser.py
secbench/api/simulation/scope.py
secbench/api/simulation/table.py
secbench_api-1.8.1.dist-info/licenses/LICENSE
secbench_api-1.8.1.dist-info/METADATA
secbench_api-1.8.1.dist-info/WHEEL
secbench_api-1.8.1.dist-info/top_level.txt
secbench_api-1.8.1.dist-info/RECORD
