Metadata-Version: 2.4
Name: secbench-api
Version: 1.8.1
Summary: Common definition and interfaces used in the Secbench framework
Author-email: Secbench team <support@secbench.fr>
License: 
Project-URL: Homepage, https://doc.secbench.fr
Project-URL: Bug Reports, https://github.com/CEA-Leti/secbench/issues
Project-URL: Source, https://github.com/CEA-Leti/secbench
Classifier: Programming Language :: Python :: 3
Classifier: Programming Language :: Python :: 3 :: Only
Classifier: Programming Language :: Python :: 3.10
Classifier: Programming Language :: Python :: 3.11
Classifier: Programming Language :: Python :: 3.12
Classifier: Programming Language :: Python :: 3.13
Classifier: Topic :: Security
Classifier: Topic :: Scientific/Engineering
Classifier: Intended Audience :: Developers
Classifier: Intended Audience :: Science/Research
Classifier: License :: OSI Approved :: CEA CNRS Inria Logiciel Libre License, version 2.1 (CeCILL-2.1)
Requires-Python: >=3.8
License-File: LICENSE
Requires-Dist: pyserial>=3.5
Requires-Dist: pyusb>=1.2; sys_platform == "linux" or sys_platform == "darwin"
Requires-Dist: PyVISA>=1.11
Requires-Dist: numpy>=1.20
Requires-Dist: python-vxi11>=0.9
Requires-Dist: pyudev>=0.24; sys_platform == "linux"
Requires-Dist: toml>=0.10; python_version < "3.11"
Requires-Dist: typing-extensions>=4.0.0
Dynamic: license-file
